<ROOT><Time TimeStamp="2016/07/26 09:45:23" /><S Code="BST" N="Baker Street."><P N="Southbound - Platform 7" Code="1" Next="0"><T S="365" T="4" D="477" C="4:30" L="At St. John's Wood Platform 2" DE="West Ham" /><T S="337" T="5" D="423" C="4:30" L="At Swiss Cottage Platform 2" DE="Stratford" /><T S="350" T="6" D="423" C="7:00" L="At Finchley Road Platform 3" DE="Stratford" /><T S="331" T="5" D="423" C="9:00" L="Between Kilburn and West Hampstead" DE="Stratford" /><T S="360" T="5" D="333" C="13:00" L="Leaving Willesden Green" DE="North Greenwich" /><T S="311" T="4" D="423" C="16:00" L="Leaving Dollis Hill" DE="Stratford" /><T S="366" T="4" D="477" C="20:00" L="Between Wembley Park and Neasden" DE="West Ham" /><T S="340" T="5" D="423" C="21:00" L="At Wembley Park Platform 4" DE="Stratford" /><T S="332" T="4" D="423" C="27:00" L="Between Queensbury and Kingsbury" DE="Stratford" /><T S="312" T="5" D="423" C="30:00" L="Leaving Canons Park" DE="Stratford" /></P><P N="Northbound - Platform 10" Code="0" Next="0"><T S="304" T="4" D="416" C="1:00" L="Between Bond Street and Baker Street" DE="Stanmore" /><T S="352" T="6" D="496" C="4:00" L="Between Green Park and Bond Street" DE="Willesden Green" /><T S="326" T="6" D="416" C="6:00" L="Between Westminster and Green Park" DE="Stanmore" /><T S="334" T="6" D="590" C="10:00" L="At Waterloo Platform 5" DE="Wembley Park" /><T S="372" T="5" D="416" C="11:00" L="Between London Bridge and Southwark" DE="Stanmore" /><T S="355" T="6" D="416" C="13:00" L="Between Bermondsey and London Bridge" DE="Stanmore" /><T S="336" T="5" D="416" C="16:00" L="Between Canada Water and Bermondsey" DE="Stanmore" /><T S="354" T="8" D="590" C="19:00" L="Between Canary Wharf and Canada Water" DE="Wembley Park" /><T S="316" T="5" D="416" C="22:00" L="Between North Greenwich and Canary Wharf" DE="Stanmore" /><T S="327" T="5" D="416" C="25:00" L="Between Canning Town and North Greenwich" DE="Stanmore" /><T S="325" T="5" D="496" C="28:00" L="Approaching Canning Town" DE="Willesden Green" /><T S="345" T="3" D="416" C="29:00" L="At West Ham Platform 5" DE="Stanmore" /></P></S><S Code="BER" N="Bermondsey."><P N="Westbound - Platform 1" Code="0" Next="0"><T S="336" T="5" D="416" C="1:00" L="Between Canada Water and Bermondsey" DE="Stanmore" /><T S="354" T="8" D="590" C="4:00" L="Between Canary Wharf and Canada Water" DE="Wembley Park" /><T S="316" T="5" D="416" C="7:00" L="Between North Greenwich and Canary Wharf" DE="Stanmore" /><T S="327" T="5" D="416" C="10:00" L="Between Canning Town and North Greenwich" DE="Stanmore" /><T S="325" T="5" D="496" C="12:00" L="Approaching Canning Town" DE="Willesden Green" /><T S="345" T="3" D="416" C="14:00" L="At West Ham Platform 5" DE="Stanmore" /></P><P N="Eastbound - Platform 2" Code="1" Next="0"><T S="320" T="5" D="423" C="-" L="At Platform" DE="Stratford" /><T S="364" T="5" D="477" C="1:30" L="Between London Bridge and Bermondsey" DE="West Ham" /><T S="305" T="5" D="423" C="4:00" L="Left Southwark" DE="Stratford" /><T S="347" T="5" D="423" C="5:00" L="Left Waterloo" DE="Stratford" /><T S="330" T="7" D="423" C="7:00" L="Left Westminster" DE="Stratford" /><T S="357" T="7" D="333" C="9:00" L="At Green Park Platform 6" DE="North Greenwich" /><T S="310" T="6" D="423" C="13:00" L="Approaching Bond Street" DE="Stratford" /><T S="321" T="5" D="423" C="14:00" L="Leaving Baker Street" DE="Stratford" /><T S="365" T="4" D="477" C="18:00" L="At St. John's Wood Platform 2" DE="West Ham" /><T S="337" T="5" D="423" C="19:00" L="At Swiss Cottage Platform 2" DE="Stratford" /><T S="350" T="6" D="423" C="22:00" L="At Finchley Road Platform 3" DE="Stratford" /><T S="331" T="5" D="423" C="24:00" L="Between Kilburn and West Hampstead" DE="Stratford" /><T S="360" T="5" D="333" C="27:00" L="Leaving Willesden Green" DE="North Greenwich" /></P></S><S Code="BDS" N="Bond Street."><P N="Northbound - Platform 3" Code="0" Next="0"><T S="352" T="6" D="496" C="0:30" L="Between Green Park and Bond Street" DE="Willesden Green" /><T S="326" T="6" D="416" C="3:00" L="Between Westminster and Green Park" DE="Stanmore" /><T S="334" T="6" D="590" C="6:00" L="At Waterloo Platform 5" DE="Wembley Park" /><T S="372" T="5" D="416" C="8:00" L="Between London Bridge and Southwark" DE="Stanmore" /><T S="355" T="6" D="416" C="10:00" L="Between Bermondsey and London Bridge" DE="Stanmore" /><T S="336" T="5" D="416" C="13:00" L="Between Canada Water and Bermondsey" DE="Stanmore" /><T S="354" T="8" D="590" C="16:00" L="Between Canary Wharf and Canada Water" DE="Wembley Park" /><T S="316" T="5" D="416" C="19:00" L="Between North Greenwich and Canary Wharf" DE="Stanmore" /><T S="327" T="5" D="416" C="22:00" L="Between Canning Town and North Greenwich" DE="Stanmore" /><T S="325" T="5" D="496" C="24:00" L="Approaching Canning Town" DE="Willesden Green" /><T S="345" T="3" D="416" C="26:00" L="At West Ham Platform 5" DE="Stanmore" /></P><P N="Southbound - Platform 4" Code="1" Next="0"><T S="310" T="6" D="423" C="0:30" L="Approaching Bond Street" DE="Stratford" /><T S="321" T="5" D="423" C="2:00" L="Leaving Baker Street" DE="Stratford" /><T S="365" T="4" D="477" C="6:00" L="At St. John's Wood Platform 2" DE="West Ham" /><T S="337" T="5" D="423" C="7:00" L="At Swiss Cottage Platform 2" DE="Stratford" /><T S="350" T="6" D="423" C="9:00" L="At Finchley Road Platform 3" DE="Stratford" /><T S="331" T="5" D="423" C="12:00" L="Between Kilburn and West Hampstead" DE="Stratford" /><T S="360" T="5" D="333" C="15:00" L="Leaving Willesden Green" DE="North Greenwich" /><T S="311" T="4" D="423" C="18:00" L="Leaving Dollis Hill" DE="Stratford" /><T S="366" T="4" D="477" C="22:00" L="Between Wembley Park and Neasden" DE="West Ham" /><T S="340" T="5" D="423" C="24:00" L="At Wembley Park Platform 4" DE="Stratford" /><T S="332" T="4" D="423" C="29:00" L="Between Queensbury and Kingsbury" DE="Stratford" /></P></S><S Code="CWR" N="Canada Water."><P N="Westbound - Platform 1" Code="0" Next="0"><T S="354" T="8" D="590" C="3:00" L="Between Canary Wharf and Canada Water" DE="Wembley Park" /><T S="316" T="5" D="416" C="5:00" L="Between North Greenwich and Canary Wharf" DE="Stanmore" /><T S="327" T="5" D="416" C="9:00" L="Between Canning Town and North Greenwich" DE="Stanmore" /><T S="325" T="5" D="496" C="11:00" L="Approaching Canning Town" DE="Willesden Green" /><T S="345" T="3" D="416" C="13:00" L="At West Ham Platform 5" DE="Stanmore" /></P><P N="Eastbound - Platform 2" Code="1" Next="0"><T S="320" T="5" D="423" C="3:00" L="At Bermondsey Platform 2" DE="Stratford" /><T S="364" T="5" D="477" C="4:00" L="Between London Bridge and Bermondsey" DE="West Ham" /><T S="305" T="5" D="423" C="6:00" L="Left Southwark" DE="Stratford" /><T S="347" T="5" D="423" C="8:00" L="Left Waterloo" DE="Stratford" /><T S="330" T="7" D="423" C="10:00" L="Left Westminster" DE="Stratford" /><T S="357" T="7" D="333" C="12:00" L="At Green Park Platform 6" DE="North Greenwich" /><T S="310" T="6" D="423" C="15:00" L="Approaching Bond Street" DE="Stratford" /><T S="321" T="5" D="423" C="17:00" L="Leaving Baker Street" DE="Stratford" /><T S="365" T="4" D="477" C="21:00" L="At St. John's Wood Platform 2" DE="West Ham" /><T S="337" T="5" D="423" C="22:00" L="At Swiss Cottage Platform 2" DE="Stratford" /><T S="350" T="6" D="423" C="25:00" L="At Finchley Road Platform 3" DE="Stratford" /><T S="331" T="5" D="423" C="27:00" L="Between Kilburn and West Hampstead" DE="Stratford" /></P></S><S Code="CWF" N="Canary Wharf."><P N="Westbound - Platform 1" Code="0" Next="0"><T S="316" T="5" D="416" C="3:00" L="Between North Greenwich and Canary Wharf" DE="Stanmore" /><T S="327" T="5" D="416" C="6:00" L="Between Canning Town and North Greenwich" DE="Stanmore" /><T S="325" T="5" D="496" C="8:00" L="Approaching Canning Town" DE="Willesden Green" /><T S="345" T="3" D="416" C="10:00" L="At West Ham Platform 5" DE="Stanmore" /></P><P N="Eastbound - Platform 2" Code="1" Next="0"><T S="307" T="5" D="423" C="0:30" L="Approaching Canary Wharf" DE="Stratford" /><T S="320" T="5" D="423" C="5:00" L="At Bermondsey Platform 2" DE="Stratford" /><T S="364" T="5" D="477" C="6:00" L="Between London Bridge and Bermondsey" DE="West Ham" /><T S="305" T="5" D="423" C="9:00" L="Left Southwark" DE="Stratford" /><T S="347" T="5" D="423" C="10:00" L="Left Waterloo" DE="Stratford" /><T S="330" T="7" D="423" C="12:00" L="Left Westminster" DE="Stratford" /><T S="357" T="7" D="333" C="14:00" L="At Green Park Platform 6" DE="North Greenwich" /><T S="310" T="6" D="423" C="18:00" L="Approaching Bond Street" DE="Stratford" /><T S="321" T="5" D="423" C="19:00" L="Leaving Baker Street" DE="Stratford" /><T S="365" T="4" D="477" C="24:00" L="At St. John's Wood Platform 2" DE="West Ham" /><T S="337" T="5" D="423" C="25:00" L="At Swiss Cottage Platform 2" DE="Stratford" /><T S="350" T="6" D="423" C="27:00" L="At Finchley Road Platform 3" DE="Stratford" /><T S="331" T="5" D="423" C="29:00" L="Between Kilburn and West Hampstead" DE="Stratford" /></P></S><S Code="CNT" N="Canning Town."><P N="Westbound - Platform 5" Code="0" Next="0"><T S="325" T="5" D="496" C="1:30" L="Approaching Canning Town" DE="Willesden Green" /><T S="345" T="3" D="416" C="3:00" L="At West Ham Platform 5" DE="Stanmore" /></P><P N="Eastbound - Platform 6" Code="1" Next="0"><T S="346" T="4" D="423" C="0:30" L="Between North Greenwich and Canning Town" DE="Stratford" /><T S="361" T="5" D="423" C="2:30" L="At North Greenwich Platform 3" DE="Stratford" /><T S="307" T="5" D="423" C="5:00" L="Approaching Canary Wharf" DE="Stratford" /><T S="320" T="5" D="423" C="10:00" L="At Bermondsey Platform 2" DE="Stratford" /><T S="364" T="5" D="477" C="11:00" L="Between London Bridge and Bermondsey" DE="West Ham" /><T S="305" T="5" D="423" C="14:00" L="Left Southwark" DE="Stratford" /><T S="347" T="5" D="423" C="15:00" L="Left Waterloo" DE="Stratford" /><T S="330" T="7" D="423" C="17:00" L="Left Westminster" DE="Stratford" /><T S="310" T="6" D="423" C="23:00" L="Approaching Bond Street" DE="Stratford" /><T S="321" T="5" D="423" C="24:00" L="Leaving Baker Street" DE="Stratford" /><T S="365" T="4" D="477" C="29:00" L="At St. John's Wood Platform 2" DE="West Ham" /><T S="337" T="5" D="423" C="30:00" L="At Swiss Cottage Platform 2" DE="Stratford" /></P></S><S Code="CPK" N="Canons Park."><P N="Northbound - Platform 1" Code="0" Next="0"><T S="302" T="4" D="416" C="-" L="At Platform" DE="Stanmore" /><T S="313" T="4" D="416" C="2:30" L="At Queensbury Platform 1" DE="Stanmore" /><T S="370" T="4" D="416" C="5:00" L="Approaching Kingsbury" DE="Stanmore" /><T S="342" T="4" D="416" C="7:00" L="Between Wembley Park and Kingsbury" DE="Stanmore" /><T S="353" T="4" D="416" C="10:00" L="Between Neasden and Wembley Park" DE="Stanmore" /><T S="303" T="4" D="416" C="14:00" L="Between Willesden Green and Dollis Hill" DE="Stanmore" /><T S="314" T="6" D="416" C="16:00" L="At Willesden Green Platform 2" DE="Stanmore" /><T S="371" T="5" D="416" C="19:00" L="Leaving West Hampstead" DE="Stanmore" /><T S="343" T="6" D="416" C="22:00" L="At Finchley Road Platform 2" DE="Stanmore" /><T S="335" T="6" D="416" C="28:00" L="Leaving Baker Street" DE="Stanmore" /></P><P N="Southbound - Platform 2" Code="1" Next="0"><T S="333" T="5" D="423" C="2:30" L="At Stanmore Platform 1" DE="Stratford" /></P></S><S Code="DHL" N="Dollis Hill."><P N="Northbound - Platform 1" Code="0" Next="0"><T S="303" T="4" D="416" C="0:30" L="Between Willesden Green and Dollis Hill" DE="Stanmore" /><T S="314" T="6" D="416" C="3:00" L="At Willesden Green Platform 2" DE="Stanmore" /><T S="371" T="5" D="416" C="5:00" L="Leaving West Hampstead" DE="Stanmore" /><T S="343" T="6" D="416" C="8:00" L="At Finchley Road Platform 2" DE="Stanmore" /><T S="324" T="8" D="590" C="12:00" L="At St. John's Wood Platform 1" DE="Wembley Park" /><T S="335" T="6" D="416" C="14:00" L="Leaving Baker Street" DE="Stanmore" /><T S="304" T="4" D="416" C="16:00" L="Between Bond Street and Baker Street" DE="Stanmore" /><T S="326" T="6" D="416" C="22:00" L="Between Westminster and Green Park" DE="Stanmore" /><T S="334" T="6" D="590" C="25:00" L="At Waterloo Platform 5" DE="Wembley Park" /><T S="372" T="5" D="416" C="27:00" L="Between London Bridge and Southwark" DE="Stanmore" /><T S="355" T="6" D="416" C="29:00" L="Between Bermondsey and London Bridge" DE="Stanmore" /></P><P N="Southbound - Platform 2" Code="1" Next="0"><T S="366" T="4" D="477" C="4:00" L="Between Wembley Park and Neasden" DE="West Ham" /><T S="340" T="5" D="423" C="5:00" L="At Wembley Park Platform 4" DE="Stratford" /><T S="332" T="4" D="423" C="11:00" L="Between Queensbury and Kingsbury" DE="Stratford" /><T S="312" T="5" D="423" C="14:00" L="Leaving Canons Park" DE="Stratford" /><T S="333" T="5" D="423" C="16:00" L="At Stanmore Platform 1" DE="Stratford" /></P></S><S Code="FRD" N="Finchley Road."><P N="Northbound - Platform 1" Code="0" Next="0" /><P N="Northbound - Platform 2" Code="0" Next="0"><T S="343" T="6" D="416" C="-" L="At Platform" DE="Stanmore" /><T S="324" T="8" D="590" C="4:00" L="At St. John's Wood Platform 1" DE="Wembley Park" /><T S="335" T="6" D="416" C="6:00" L="Leaving Baker Street" DE="Stanmore" /><T S="304" T="4" D="416" C="8:00" L="Between Bond Street and Baker Street" DE="Stanmore" /><T S="352" T="6" D="496" C="11:00" L="Between Green Park and Bond Street" DE="Willesden Green" /><T S="326" T="6" D="416" C="14:00" L="Between Westminster and Green Park" DE="Stanmore" /><T S="334" T="6" D="590" C="17:00" L="At Waterloo Platform 5" DE="Wembley Park" /><T S="372" T="5" D="416" C="19:00" L="Between London Bridge and Southwark" DE="Stanmore" /><T S="355" T="6" D="416" C="21:00" L="Between Bermondsey and London Bridge" DE="Stanmore" /><T S="336" T="5" D="416" C="24:00" L="Between Canada Water and Bermondsey" DE="Stanmore" /><T S="354" T="8" D="590" C="27:00" L="Between Canary Wharf and Canada Water" DE="Wembley Park" /><T S="316" T="5" D="416" C="30:00" L="Between North Greenwich and Canary Wharf" DE="Stanmore" /></P><P N="Southbound - Platform 3" Code="1" Next="0"><T S="350" T="6" D="423" C="-" L="At Platform" DE="Stratford" /><T S="331" T="5" D="423" C="2:30" L="Between Kilburn and West Hampstead" DE="Stratford" /><T S="360" T="5" D="333" C="5:00" L="Leaving Willesden Green" DE="North Greenwich" /><T S="311" T="4" D="423" C="9:00" L="Leaving Dollis Hill" DE="Stratford" /><T S="366" T="4" D="477" C="13:00" L="Between Wembley Park and Neasden" DE="West Ham" /><T S="340" T="5" D="423" C="14:00" L="At Wembley Park Platform 4" DE="Stratford" /><T S="332" T="4" D="423" C="20:00" L="Between Queensbury and Kingsbury" DE="Stratford" /><T S="312" T="5" D="423" C="23:00" L="Leaving Canons Park" DE="Stratford" /><T S="333" T="5" D="423" C="25:00" L="At Stanmore Platform 1" DE="Stratford" /></P><P N="Southbound - Platform 4" Code="1" Next="0" /></S><S Code="GPK" N="Green Park."><P N="Northbound - Platform 5" Code="0" Next="0"><T S="326" T="6" D="416" C="1:00" L="Between Westminster and Green Park" DE="Stanmore" /><T S="334" T="6" D="590" C="4:30" L="At Waterloo Platform 5" DE="Wembley Park" /><T S="372" T="5" D="416" C="6:00" L="Between London Bridge and Southwark" DE="Stanmore" /><T S="355" T="6" D="416" C="8:00" L="Between Bermondsey and London Bridge" DE="Stanmore" /><T S="336" T="5" D="416" C="11:00" L="Between Canada Water and Bermondsey" DE="Stanmore" /><T S="354" T="8" D="590" C="14:00" L="Between Canary Wharf and Canada Water" DE="Wembley Park" /><T S="316" T="5" D="416" C="16:00" L="Between North Greenwich and Canary Wharf" DE="Stanmore" /><T S="327" T="5" D="416" C="20:00" L="Between Canning Town and North Greenwich" DE="Stanmore" /><T S="325" T="5" D="496" C="22:00" L="Approaching Canning Town" DE="Willesden Green" /><T S="345" T="3" D="416" C="24:00" L="At West Ham Platform 5" DE="Stanmore" /></P><P N="Southbound - Platform 6" Code="1" Next="0"><T S="357" T="7" D="333" C="-" L="At Platform" DE="North Greenwich" /><T S="310" T="6" D="423" C="3:00" L="Approaching Bond Street" DE="Stratford" /><T S="321" T="5" D="423" C="4:30" L="Leaving Baker Street" DE="Stratford" /><T S="365" T="4" D="477" C="8:00" L="At St. John's Wood Platform 2" DE="West Ham" /><T S="337" T="5" D="423" C="9:00" L="At Swiss Cottage Platform 2" DE="Stratford" /><T S="350" T="6" D="423" C="12:00" L="At Finchley Road Platform 3" DE="Stratford" /><T S="331" T="5" D="423" C="14:00" L="Between Kilburn and West Hampstead" DE="Stratford" /><T S="360" T="5" D="333" C="17:00" L="Leaving Willesden Green" DE="North Greenwich" /><T S="311" T="4" D="423" C="21:00" L="Leaving Dollis Hill" DE="Stratford" /><T S="366" T="4" D="477" C="25:00" L="Between Wembley Park and Neasden" DE="West Ham" /><T S="340" T="5" D="423" C="26:00" L="At Wembley Park Platform 4" DE="Stratford" /></P></S><S Code="KIL" N="Kilburn."><P N="Northbound - Platform 1" Code="0" Next="0"><T S="371" T="5" D="416" C="1:00" L="Leaving West Hampstead" DE="Stanmore" /><T S="301" T="6" D="496" C="2:30" L="Between Finchley Road and West Hampstead" DE="Willesden Green" /><T S="343" T="6" D="416" C="4:00" L="At Finchley Road Platform 2" DE="Stanmore" /><T S="324" T="8" D="590" C="7:00" L="At St. John's Wood Platform 1" DE="Wembley Park" /><T S="335" T="6" D="416" C="10:00" L="Leaving Baker Street" DE="Stanmore" /><T S="304" T="4" D="416" C="12:00" L="Between Bond Street and Baker Street" DE="Stanmore" /><T S="352" T="6" D="496" C="15:00" L="Between Green Park and Bond Street" DE="Willesden Green" /><T S="326" T="6" D="416" C="17:00" L="Between Westminster and Green Park" DE="Stanmore" /><T S="334" T="6" D="590" C="21:00" L="At Waterloo Platform 5" DE="Wembley Park" /><T S="372" T="5" D="416" C="22:00" L="Between London Bridge and Southwark" DE="Stanmore" /><T S="355" T="6" D="416" C="25:00" L="Between Bermondsey and London Bridge" DE="Stanmore" /><T S="336" T="5" D="416" C="28:00" L="Between Canada Water and Bermondsey" DE="Stanmore" /></P><P N="Southbound - Platform 2" Code="1" Next="0"><T S="360" T="5" D="333" C="2:30" L="Leaving Willesden Green" DE="North Greenwich" /><T S="311" T="4" D="423" C="5:00" L="Leaving Dollis Hill" DE="Stratford" /><T S="366" T="4" D="477" C="10:00" L="Between Wembley Park and Neasden" DE="West Ham" /><T S="340" T="5" D="423" C="11:00" L="At Wembley Park Platform 4" DE="Stratford" /><T S="332" T="4" D="423" C="17:00" L="Between Queensbury and Kingsbury" DE="Stratford" /><T S="312" T="5" D="423" C="19:00" L="Leaving Canons Park" DE="Stratford" /><T S="333" T="5" D="423" C="22:00" L="At Stanmore Platform 1" DE="Stratford" /></P></S><S Code="KBY" N="Kingsbury."><P N="Northbound - Platform 1" Code="0" Next="0"><T S="370" T="4" D="416" C="-" L="At Platform" DE="Stanmore" /><T S="342" T="4" D="416" C="3:00" L="Between Wembley Park and Kingsbury" DE="Stanmore" /><T S="353" T="4" D="416" C="5:00" L="Between Neasden and Wembley Park" DE="Stanmore" /><T S="303" T="4" D="416" C="9:00" L="Between Willesden Green and Dollis Hill" DE="Stanmore" /><T S="314" T="6" D="416" C="12:00" L="At Willesden Green Platform 2" DE="Stanmore" /><T S="371" T="5" D="416" C="14:00" L="Leaving West Hampstead" DE="Stanmore" /><T S="343" T="6" D="416" C="17:00" L="At Finchley Road Platform 2" DE="Stanmore" /><T S="335" T="6" D="416" C="23:00" L="Leaving Baker Street" DE="Stanmore" /><T S="304" T="4" D="416" C="26:00" L="Between Bond Street and Baker Street" DE="Stanmore" /></P><P N="Southbound - Platform 2" Code="1" Next="0"><T S="332" T="4" D="423" C="1:30" L="Between Queensbury and Kingsbury" DE="Stratford" /><T S="312" T="5" D="423" C="4:00" L="Leaving Canons Park" DE="Stratford" /><T S="333" T="5" D="423" C="6:00" L="At Stanmore Platform 1" DE="Stratford" /></P></S><S Code="LON" N="London Bridge."><P N="Westbound - Platform 3" Code="0" Next="0"><T S="355" T="6" D="416" C="0:30" L="Between Bermondsey and London Bridge" DE="Stanmore" /><T S="336" T="5" D="416" C="3:30" L="Between Canada Water and Bermondsey" DE="Stanmore" /><T S="354" T="8" D="590" C="6:00" L="Between Canary Wharf and Canada Water" DE="Wembley Park" /><T S="316" T="5" D="416" C="9:00" L="Between North Greenwich and Canary Wharf" DE="Stanmore" /><T S="327" T="5" D="416" C="12:00" L="Between Canning Town and North Greenwich" DE="Stanmore" /><T S="325" T="5" D="496" C="15:00" L="Approaching Canning Town" DE="Willesden Green" /><T S="345" T="3" D="416" C="16:00" L="At West Ham Platform 5" DE="Stanmore" /></P><P N="Eastbound - Platform 4" Code="1" Next="0"><T S="305" T="5" D="423" C="1:30" L="Left Southwark" DE="Stratford" /><T S="347" T="5" D="423" C="2:30" L="Left Waterloo" DE="Stratford" /><T S="330" T="7" D="423" C="4:30" L="Left Westminster" DE="Stratford" /><T S="357" T="7" D="333" C="7:00" L="At Green Park Platform 6" DE="North Greenwich" /><T S="310" T="6" D="423" C="10:00" L="Approaching Bond Street" DE="Stratford" /><T S="321" T="5" D="423" C="11:00" L="Leaving Baker Street" DE="Stratford" /><T S="365" T="4" D="477" C="16:00" L="At St. John's Wood Platform 2" DE="West Ham" /><T S="337" T="5" D="423" C="17:00" L="At Swiss Cottage Platform 2" DE="Stratford" /><T S="350" T="6" D="423" C="19:00" L="At Finchley Road Platform 3" DE="Stratford" /><T S="331" T="5" D="423" C="21:00" L="Between Kilburn and West Hampstead" DE="Stratford" /><T S="360" T="5" D="333" C="25:00" L="Leaving Willesden Green" DE="North Greenwich" /><T S="311" T="4" D="423" C="28:00" L="Leaving Dollis Hill" DE="Stratford" /></P></S><S Code="NEA" N="Neasden."><P N="Northbound - Platform 2" Code="0" Next="0"><T S="367" T="5" D="590" C="2:00" L="Leaving Dollis Hill" DE="Wembley Park" /><T S="303" T="4" D="416" C="3:00" L="Between Willesden Green and Dollis Hill" DE="Stanmore" /><T S="314" T="6" D="416" C="5:00" L="At Willesden Green Platform 2" DE="Stanmore" /><T S="371" T="5" D="416" C="8:00" L="Leaving West Hampstead" DE="Stanmore" /><T S="343" T="6" D="416" C="11:00" L="At Finchley Road Platform 2" DE="Stanmore" /><T S="324" T="8" D="590" C="14:00" L="At St. John's Wood Platform 1" DE="Wembley Park" /><T S="335" T="6" D="416" C="17:00" L="Leaving Baker Street" DE="Stanmore" /><T S="304" T="4" D="416" C="19:00" L="Between Bond Street and Baker Street" DE="Stanmore" /><T S="326" T="6" D="416" C="24:00" L="Between Westminster and Green Park" DE="Stanmore" /><T S="334" T="6" D="590" C="28:00" L="At Waterloo Platform 5" DE="Wembley Park" /><T S="372" T="5" D="416" C="29:00" L="Between London Bridge and Southwark" DE="Stanmore" /></P><P N="Southbound - Platform 3" Code="1" Next="0"><T S="366" T="4" D="477" C="2:30" L="Between Wembley Park and Neasden" DE="West Ham" /><T S="340" T="5" D="423" C="4:00" L="At Wembley Park Platform 4" DE="Stratford" /><T S="332" T="4" D="423" C="10:00" L="Between Queensbury and Kingsbury" DE="Stratford" /><T S="312" T="5" D="423" C="12:00" L="Leaving Canons Park" DE="Stratford" /><T S="333" T="5" D="423" C="15:00" L="At Stanmore Platform 1" DE="Stratford" /></P></S><S Code="NGW" N="North Greenwich."><P N="Westbound - Platform 1" Code="0" Next="0"><T S="327" T="5" D="416" C="3:00" L="Between Canning Town and North Greenwich" DE="Stanmore" /><T S="325" T="5" D="496" C="5:00" L="Approaching Canning Town" DE="Willesden Green" /><T S="345" T="3" D="416" C="6:00" L="At West Ham Platform 5" DE="Stanmore" /></P><P N="Westbound - Platform 2" Code="0" Next="0"><T S="356" T="4" D="333" C="1:00" L="Between Canary Wharf and North Greenwich" DE="North Greenwich" /><T S="357" T="7" D="333" C="17:00" L="At Green Park Platform 6" DE="North Greenwich" /></P><P N="Eastbound - Platform 3" Code="1" Next="0"><T S="361" T="5" D="423" C="-" L="At Platform" DE="Stratford" /><T S="307" T="5" D="423" C="3:00" L="Approaching Canary Wharf" DE="Stratford" /><T S="320" T="5" D="423" C="8:00" L="At Bermondsey Platform 2" DE="Stratford" /><T S="364" T="5" D="477" C="9:00" L="Between London Bridge and Bermondsey" DE="West Ham" /><T S="305" T="5" D="423" C="11:00" L="Left Southwark" DE="Stratford" /><T S="347" T="5" D="423" C="13:00" L="Left Waterloo" DE="Stratford" /><T S="330" T="7" D="423" C="15:00" L="Left Westminster" DE="Stratford" /><T S="310" T="6" D="423" C="21:00" L="Approaching Bond Street" DE="Stratford" /><T S="321" T="5" D="423" C="22:00" L="Leaving Baker Street" DE="Stratford" /><T S="365" T="4" D="477" C="26:00" L="At St. John's Wood Platform 2" DE="West Ham" /><T S="337" T="5" D="423" C="27:00" L="At Swiss Cottage Platform 2" DE="Stratford" /><T S="350" T="6" D="423" C="30:00" L="At Finchley Road Platform 3" DE="Stratford" /></P></S><S Code="QBY" N="Queensbury."><P N="Northbound - Platform 1" Code="0" Next="0"><T S="313" T="4" D="416" C="-" L="At Platform" DE="Stanmore" /><T S="370" T="4" D="416" C="3:00" L="Approaching Kingsbury" DE="Stanmore" /><T S="342" T="4" D="416" C="5:00" L="Between Wembley Park and Kingsbury" DE="Stanmore" /><T S="353" T="4" D="416" C="7:00" L="Between Neasden and Wembley Park" DE="Stanmore" /><T S="303" T="4" D="416" C="11:00" L="Between Willesden Green and Dollis Hill" DE="Stanmore" /><T S="314" T="6" D="416" C="14:00" L="At Willesden Green Platform 2" DE="Stanmore" /><T S="371" T="5" D="416" C="16:00" L="Leaving West Hampstead" DE="Stanmore" /><T S="343" T="6" D="416" C="19:00" L="At Finchley Road Platform 2" DE="Stanmore" /><T S="335" T="6" D="416" C="25:00" L="Leaving Baker Street" DE="Stanmore" /><T S="304" T="4" D="416" C="28:00" L="Between Bond Street and Baker Street" DE="Stanmore" /></P><P N="Southbound - Platform 2" Code="1" Next="0"><T S="312" T="5" D="423" C="2:30" L="Leaving Canons Park" DE="Stratford" /><T S="333" T="5" D="423" C="5:00" L="At Stanmore Platform 1" DE="Stratford" /></P></S><S Code="SWK" N="Southwark."><P N="Westbound - Platform 1" Code="0" Next="0"><T S="372" T="5" D="416" C="0:30" L="Between London Bridge and Southwark" DE="Stanmore" /><T S="355" T="6" D="416" C="2:30" L="Between Bermondsey and London Bridge" DE="Stanmore" /><T S="336" T="5" D="416" C="5:00" L="Between Canada Water and Bermondsey" DE="Stanmore" /><T S="354" T="8" D="590" C="8:00" L="Between Canary Wharf and Canada Water" DE="Wembley Park" /><T S="316" T="5" D="416" C="11:00" L="Between North Greenwich and Canary Wharf" DE="Stanmore" /><T S="327" T="5" D="416" C="15:00" L="Between Canning Town and North Greenwich" DE="Stanmore" /><T S="325" T="5" D="496" C="17:00" L="Approaching Canning Town" DE="Willesden Green" /><T S="345" T="3" D="416" C="18:00" L="At West Ham Platform 5" DE="Stanmore" /></P><P N="Eastbound - Platform 2" Code="1" Next="0"><T S="347" T="5" D="423" C="1:30" L="Left Waterloo" DE="Stratford" /><T S="330" T="7" D="423" C="3:30" L="Left Westminster" DE="Stratford" /><T S="357" T="7" D="333" C="5:00" L="At Green Park Platform 6" DE="North Greenwich" /><T S="310" T="6" D="423" C="9:00" L="Approaching Bond Street" DE="Stratford" /><T S="321" T="5" D="423" C="10:00" L="Leaving Baker Street" DE="Stratford" /><T S="365" T="4" D="477" C="14:00" L="At St. John's Wood Platform 2" DE="West Ham" /><T S="337" T="5" D="423" C="15:00" L="At Swiss Cottage Platform 2" DE="Stratford" /><T S="350" T="6" D="423" C="18:00" L="At Finchley Road Platform 3" DE="Stratford" /><T S="331" T="5" D="423" C="20:00" L="Between Kilburn and West Hampstead" DE="Stratford" /><T S="360" T="5" D="333" C="23:00" L="Leaving Willesden Green" DE="North Greenwich" /><T S="311" T="4" D="423" C="27:00" L="Leaving Dollis Hill" DE="Stratford" /></P></S><S Code="SJW" N="St. John's Wood."><P N="Northbound - Platform 1" Code="0" Next="0"><T S="324" T="8" D="590" C="-" L="At Platform" DE="Wembley Park" /><T S="335" T="6" D="416" C="3:00" L="Leaving Baker Street" DE="Stanmore" /><T S="304" T="4" D="416" C="5:00" L="Between Bond Street and Baker Street" DE="Stanmore" /><T S="352" T="6" D="496" C="8:00" L="Between Green Park and Bond Street" DE="Willesden Green" /><T S="326" T="6" D="416" C="10:00" L="Between Westminster and Green Park" DE="Stanmore" /><T S="334" T="6" D="590" C="14:00" L="At Waterloo Platform 5" DE="Wembley Park" /><T S="372" T="5" D="416" C="15:00" L="Between London Bridge and Southwark" DE="Stanmore" /><T S="355" T="6" D="416" C="17:00" L="Between Bermondsey and London Bridge" DE="Stanmore" /><T S="336" T="5" D="416" C="20:00" L="Between Canada Water and Bermondsey" DE="Stanmore" /><T S="354" T="8" D="590" C="23:00" L="Between Canary Wharf and Canada Water" DE="Wembley Park" /><T S="316" T="5" D="416" C="26:00" L="Between North Greenwich and Canary Wharf" DE="Stanmore" /><T S="327" T="5" D="416" C="30:00" L="Between Canning Town and North Greenwich" DE="Stanmore" /></P><P N="Southbound - Platform 2" Code="1" Next="0"><T S="365" T="4" D="477" C="-" L="At Platform" DE="West Ham" /><T S="337" T="5" D="423" C="1:00" L="At Swiss Cottage Platform 2" DE="Stratford" /><T S="350" T="6" D="423" C="4:00" L="At Finchley Road Platform 3" DE="Stratford" /><T S="331" T="5" D="423" C="6:00" L="Between Kilburn and West Hampstead" DE="Stratford" /><T S="360" T="5" D="333" C="9:00" L="Leaving Willesden Green" DE="North Greenwich" /><T S="311" T="4" D="423" C="12:00" L="Leaving Dollis Hill" DE="Stratford" /><T S="366" T="4" D="477" C="16:00" L="Between Wembley Park and Neasden" DE="West Ham" /><T S="340" T="5" D="423" C="18:00" L="At Wembley Park Platform 4" DE="Stratford" /><T S="332" T="4" D="423" C="24:00" L="Between Queensbury and Kingsbury" DE="Stratford" /><T S="312" T="5" D="423" C="26:00" L="Leaving Canons Park" DE="Stratford" /><T S="333" T="5" D="423" C="29:00" L="At Stanmore Platform 1" DE="Stratford" /></P></S><S Code="STA" N="Stanmore."><P N="Southbound - Platform 1" Code="1" Next="0"><T S="333" T="5" D="423" C="-" L="At Platform" DE="Stratford" /><T S="302" T="4" D="416" C="3:30" L="At Canons Park Platform 1" DE="Stanmore" /><T S="313" T="4" D="416" C="5:00" L="At Queensbury Platform 1" DE="Stanmore" /><T S="370" T="4" D="416" C="8:00" L="Approaching Kingsbury" DE="Stanmore" /><T S="342" T="4" D="416" C="10:00" L="Between Wembley Park and Kingsbury" DE="Stanmore" /><T S="353" T="4" D="416" C="13:00" L="Between Neasden and Wembley Park" DE="Stanmore" /><T S="303" T="4" D="416" C="17:00" L="Between Willesden Green and Dollis Hill" DE="Stanmore" /><T S="314" T="6" D="416" C="19:00" L="At Willesden Green Platform 2" DE="Stanmore" /><T S="371" T="5" D="416" C="22:00" L="Leaving West Hampstead" DE="Stanmore" /><T S="343" T="6" D="416" C="25:00" L="At Finchley Road Platform 2" DE="Stanmore" /></P><P N="Southbound - Platform 2" Code="1" Next="0"><T S="341" T="3" D="423" C="-" L="At Platform" DE="Stratford" /><T S="302" T="4" D="416" C="2:30" L="At Canons Park Platform 1" DE="Stanmore" /><T S="313" T="4" D="416" C="5:00" L="At Queensbury Platform 1" DE="Stanmore" /><T S="370" T="4" D="416" C="8:00" L="Approaching Kingsbury" DE="Stanmore" /><T S="342" T="4" D="416" C="10:00" L="Between Wembley Park and Kingsbury" DE="Stanmore" /><T S="353" T="4" D="416" C="12:00" L="Between Neasden and Wembley Park" DE="Stanmore" /><T S="303" T="4" D="416" C="16:00" L="Between Willesden Green and Dollis Hill" DE="Stanmore" /><T S="314" T="6" D="416" C="19:00" L="At Willesden Green Platform 2" DE="Stanmore" /><T S="371" T="5" D="416" C="21:00" L="Leaving West Hampstead" DE="Stanmore" /><T S="343" T="6" D="416" C="24:00" L="At Finchley Road Platform 2" DE="Stanmore" /></P><P N="Southbound - Platform 3" Code="1" Next="0"><T S="323" T="6" D="423" C="-" L="At Platform" DE="Stratford" /><T S="302" T="4" D="416" C="2:30" L="At Canons Park Platform 1" DE="Stanmore" /><T S="313" T="4" D="416" C="5:00" L="At Queensbury Platform 1" DE="Stanmore" /><T S="370" T="4" D="416" C="8:00" L="Approaching Kingsbury" DE="Stanmore" /><T S="342" T="4" D="416" C="10:00" L="Between Wembley Park and Kingsbury" DE="Stanmore" /><T S="353" T="4" D="416" C="12:00" L="Between Neasden and Wembley Park" DE="Stanmore" /><T S="303" T="4" D="416" C="16:00" L="Between Willesden Green and Dollis Hill" DE="Stanmore" /><T S="314" T="6" D="416" C="18:00" L="At Willesden Green Platform 2" DE="Stanmore" /><T S="371" T="5" D="416" C="21:00" L="Leaving West Hampstead" DE="Stanmore" /><T S="343" T="6" D="416" C="24:00" L="At Finchley Road Platform 2" DE="Stanmore" /></P></S><S Code="SFD" N="Stratford."><P N="Westbound - Platform 13" Code="0" Next="0"><T S="317" T="5" D="423" C="3:00" L="Between West Ham and Stratford" DE="Stratford" /><T S="315" T="6" D="423" C="5:00" L="Between Canning Town and West Ham" DE="Stratford" /><T S="346" T="4" D="423" C="7:00" L="Between North Greenwich and Canning Town" DE="Stratford" /><T S="361" T="5" D="423" C="9:00" L="At North Greenwich Platform 3" DE="Stratford" /><T S="307" T="5" D="423" C="12:00" L="Approaching Canary Wharf" DE="Stratford" /><T S="320" T="5" D="423" C="17:00" L="At Bermondsey Platform 2" DE="Stratford" /><T S="305" T="5" D="423" C="21:00" L="Left Southwark" DE="Stratford" /><T S="347" T="5" D="423" C="22:00" L="Left Waterloo" DE="Stratford" /><T S="330" T="7" D="423" C="24:00" L="Left Westminster" DE="Stratford" /><T S="310" T="6" D="423" C="30:00" L="Approaching Bond Street" DE="Stratford" /></P><P N="Westbound - Platform 14" Code="0" Next="0"><T S="306" T="7" D="423" C="-" L="At Platform" DE="Stratford" /><T S="317" T="5" D="423" C="3:00" L="Between West Ham and Stratford" DE="Stratford" /><T S="315" T="6" D="423" C="6:00" L="Between Canning Town and West Ham" DE="Stratford" /><T S="346" T="4" D="423" C="8:00" L="Between North Greenwich and Canning Town" DE="Stratford" /><T S="361" T="5" D="423" C="10:00" L="At North Greenwich Platform 3" DE="Stratford" /><T S="307" T="5" D="423" C="13:00" L="Approaching Canary Wharf" DE="Stratford" /><T S="320" T="5" D="423" C="17:00" L="At Bermondsey Platform 2" DE="Stratford" /><T S="305" T="5" D="423" C="21:00" L="Left Southwark" DE="Stratford" /><T S="347" T="5" D="423" C="23:00" L="Left Waterloo" DE="Stratford" /><T S="330" T="7" D="423" C="24:00" L="Left Westminster" DE="Stratford" /></P><P N="Westbound - Platform 15" Code="0" Next="0"><T S="344" T="4" D="590" C="-" L="At Platform" DE="Wembley Park" /><T S="317" T="5" D="423" C="2:30" L="Between West Ham and Stratford" DE="Stratford" /><T S="315" T="6" D="423" C="5:00" L="Between Canning Town and West Ham" DE="Stratford" /><T S="346" T="4" D="423" C="7:00" L="Between North Greenwich and Canning Town" DE="Stratford" /><T S="361" T="5" D="423" C="9:00" L="At North Greenwich Platform 3" DE="Stratford" /><T S="307" T="5" D="423" C="12:00" L="Approaching Canary Wharf" DE="Stratford" /><T S="320" T="5" D="423" C="17:00" L="At Bermondsey Platform 2" DE="Stratford" /><T S="305" T="5" D="423" C="21:00" L="Left Southwark" DE="Stratford" /><T S="347" T="5" D="423" C="22:00" L="Left Waterloo" DE="Stratford" /><T S="330" T="7" D="423" C="24:00" L="Left Westminster" DE="Stratford" /><T S="310" T="6" D="423" C="30:00" L="Approaching Bond Street" DE="Stratford" /></P></S><S Code="SWC" N="Swiss Cottage."><P N="Northbound - Platform 1" Code="0" Next="0"><T S="324" T="8" D="590" C="2:30" L="At St. John's Wood Platform 1" DE="Wembley Park" /><T S="335" T="6" D="416" C="5:00" L="Leaving Baker Street" DE="Stanmore" /><T S="304" T="4" D="416" C="7:00" L="Between Bond Street and Baker Street" DE="Stanmore" /><T S="352" T="6" D="496" C="10:00" L="Between Green Park and Bond Street" DE="Willesden Green" /><T S="326" T="6" D="416" C="12:00" L="Between Westminster and Green Park" DE="Stanmore" /><T S="334" T="6" D="590" C="16:00" L="At Waterloo Platform 5" DE="Wembley Park" /><T S="372" T="5" D="416" C="17:00" L="Between London Bridge and Southwark" DE="Stanmore" /><T S="355" T="6" D="416" C="19:00" L="Between Bermondsey and London Bridge" DE="Stanmore" /><T S="336" T="5" D="416" C="22:00" L="Between Canada Water and Bermondsey" DE="Stanmore" /><T S="354" T="8" D="590" C="25:00" L="Between Canary Wharf and Canada Water" DE="Wembley Park" /><T S="316" T="5" D="416" C="28:00" L="Between North Greenwich and Canary Wharf" DE="Stanmore" /></P><P N="Southbound - Platform 2" Code="1" Next="0"><T S="337" T="5" D="423" C="-" L="At Platform" DE="Stratford" /><T S="350" T="6" D="423" C="2:00" L="At Finchley Road Platform 3" DE="Stratford" /><T S="331" T="5" D="423" C="4:00" L="Between Kilburn and West Hampstead" DE="Stratford" /><T S="360" T="5" D="333" C="7:00" L="Leaving Willesden Green" DE="North Greenwich" /><T S="311" T="4" D="423" C="10:00" L="Leaving Dollis Hill" DE="Stratford" /><T S="366" T="4" D="477" C="14:00" L="Between Wembley Park and Neasden" DE="West Ham" /><T S="340" T="5" D="423" C="16:00" L="At Wembley Park Platform 4" DE="Stratford" /><T S="332" T="4" D="423" C="22:00" L="Between Queensbury and Kingsbury" DE="Stratford" /><T S="312" T="5" D="423" C="24:00" L="Leaving Canons Park" DE="Stratford" /><T S="333" T="5" D="423" C="27:00" L="At Stanmore Platform 1" DE="Stratford" /></P></S><S Code="WLO" N="Waterloo."><P N="Westbound - Platform 5" Code="0" Next="0"><T S="334" T="6" D="590" C="-" L="At Platform" DE="Wembley Park" /><T S="372" T="5" D="416" C="1:30" L="Between London Bridge and Southwark" DE="Stanmore" /><T S="355" T="6" D="416" C="4:00" L="Between Bermondsey and London Bridge" DE="Stanmore" /><T S="336" T="5" D="416" C="7:00" L="Between Canada Water and Bermondsey" DE="Stanmore" /><T S="354" T="8" D="590" C="9:00" L="Between Canary Wharf and Canada Water" DE="Wembley Park" /><T S="316" T="5" D="416" C="12:00" L="Between North Greenwich and Canary Wharf" DE="Stanmore" /><T S="327" T="5" D="416" C="16:00" L="Between Canning Town and North Greenwich" DE="Stanmore" /><T S="325" T="5" D="496" C="18:00" L="Approaching Canning Town" DE="Willesden Green" /><T S="345" T="3" D="416" C="19:00" L="At West Ham Platform 5" DE="Stanmore" /></P><P N="Eastbound - Platform 6" Code="1" Next="0"><T S="330" T="7" D="423" C="2:00" L="Left Westminster" DE="Stratford" /><T S="357" T="7" D="333" C="4:00" L="At Green Park Platform 6" DE="North Greenwich" /><T S="310" T="6" D="423" C="8:00" L="Approaching Bond Street" DE="Stratford" /><T S="321" T="5" D="423" C="9:00" L="Leaving Baker Street" DE="Stratford" /><T S="365" T="4" D="477" C="13:00" L="At St. John's Wood Platform 2" DE="West Ham" /><T S="337" T="5" D="423" C="14:00" L="At Swiss Cottage Platform 2" DE="Stratford" /><T S="350" T="6" D="423" C="17:00" L="At Finchley Road Platform 3" DE="Stratford" /><T S="331" T="5" D="423" C="19:00" L="Between Kilburn and West Hampstead" DE="Stratford" /><T S="360" T="5" D="333" C="22:00" L="Leaving Willesden Green" DE="North Greenwich" /><T S="311" T="4" D="423" C="25:00" L="Leaving Dollis Hill" DE="Stratford" /><T S="366" T="4" D="477" C="29:00" L="Between Wembley Park and Neasden" DE="West Ham" /></P></S><S Code="WPK" N="Wembley Park."><P N="Northbound - Platform 3" Code="0" Next="0"><T S="353" T="4" D="416" C="0:30" L="Between Neasden and Wembley Park" DE="Stanmore" /><T S="367" T="5" D="590" C="4:00" L="Leaving Dollis Hill" DE="Wembley Park" /><T S="303" T="4" D="416" C="5:00" L="Between Willesden Green and Dollis Hill" DE="Stanmore" /><T S="314" T="6" D="416" C="7:00" L="At Willesden Green Platform 2" DE="Stanmore" /><T S="371" T="5" D="416" C="10:00" L="Leaving West Hampstead" DE="Stanmore" /><T S="343" T="6" D="416" C="13:00" L="At Finchley Road Platform 2" DE="Stanmore" /><T S="324" T="8" D="590" C="16:00" L="At St. John's Wood Platform 1" DE="Wembley Park" /><T S="335" T="6" D="416" C="19:00" L="Leaving Baker Street" DE="Stanmore" /><T S="304" T="4" D="416" C="21:00" L="Between Bond Street and Baker Street" DE="Stanmore" /><T S="326" T="6" D="416" C="26:00" L="Between Westminster and Green Park" DE="Stanmore" /><T S="334" T="6" D="590" C="30:00" L="At Waterloo Platform 5" DE="Wembley Park" /></P><P N="Southbound - Platform 4" Code="1" Next="0"><T S="340" T="5" D="423" C="-" L="At Platform" DE="Stratford" /><T S="332" T="4" D="423" C="6:00" L="Between Queensbury and Kingsbury" DE="Stratford" /><T S="312" T="5" D="423" C="8:00" L="Leaving Canons Park" DE="Stratford" /><T S="333" T="5" D="423" C="11:00" L="At Stanmore Platform 1" DE="Stratford" /></P></S><S Code="WHM" N="West Ham."><P N="Westbound - Platform 5" Code="0" Next="0"><T S="345" T="3" D="416" C="-" L="At Platform" DE="Stanmore" /></P><P N="Eastbound - Platform 6" Code="1" Next="0"><T S="315" T="6" D="423" C="2:30" L="Between Canning Town and West Ham" DE="Stratford" /><T S="346" T="4" D="423" C="4:00" L="Between North Greenwich and Canning Town" DE="Stratford" /><T S="361" T="5" D="423" C="6:00" L="At North Greenwich Platform 3" DE="Stratford" /><T S="307" T="5" D="423" C="9:00" L="Approaching Canary Wharf" DE="Stratford" /><T S="320" T="5" D="423" C="14:00" L="At Bermondsey Platform 2" DE="Stratford" /><T S="364" T="5" D="477" C="15:00" L="Between London Bridge and Bermondsey" DE="West Ham" /><T S="305" T="5" D="423" C="17:00" L="Left Southwark" DE="Stratford" /><T S="347" T="5" D="423" C="19:00" L="Left Waterloo" DE="Stratford" /><T S="330" T="7" D="423" C="21:00" L="Left Westminster" DE="Stratford" /><T S="310" T="6" D="423" C="26:00" L="Approaching Bond Street" DE="Stratford" /><T S="321" T="5" D="423" C="28:00" L="Leaving Baker Street" DE="Stratford" /></P></S><S Code="WHD" N="West Hampstead."><P N="Northbound - Platform 1" Code="0" Next="0"><T S="301" T="6" D="496" C="0:30" L="Between Finchley Road and West Hampstead" DE="Willesden Green" /><T S="343" T="6" D="416" C="2:30" L="At Finchley Road Platform 2" DE="Stanmore" /><T S="324" T="8" D="590" C="6:00" L="At St. John's Wood Platform 1" DE="Wembley Park" /><T S="335" T="6" D="416" C="8:00" L="Leaving Baker Street" DE="Stanmore" /><T S="304" T="4" D="416" C="10:00" L="Between Bond Street and Baker Street" DE="Stanmore" /><T S="352" T="6" D="496" C="13:00" L="Between Green Park and Bond Street" DE="Willesden Green" /><T S="326" T="6" D="416" C="16:00" L="Between Westminster and Green Park" DE="Stanmore" /><T S="334" T="6" D="590" C="19:00" L="At Waterloo Platform 5" DE="Wembley Park" /><T S="372" T="5" D="416" C="21:00" L="Between London Bridge and Southwark" DE="Stanmore" /><T S="355" T="6" D="416" C="23:00" L="Between Bermondsey and London Bridge" DE="Stanmore" /><T S="336" T="5" D="416" C="26:00" L="Between Canada Water and Bermondsey" DE="Stanmore" /><T S="354" T="8" D="590" C="29:00" L="Between Canary Wharf and Canada Water" DE="Wembley Park" /></P><P N="Southbound - Platform 2" Code="1" Next="0"><T S="331" T="5" D="423" C="1:00" L="Between Kilburn and West Hampstead" DE="Stratford" /><T S="360" T="5" D="333" C="4:00" L="Leaving Willesden Green" DE="North Greenwich" /><T S="311" T="4" D="423" C="7:00" L="Leaving Dollis Hill" DE="Stratford" /><T S="366" T="4" D="477" C="11:00" L="Between Wembley Park and Neasden" DE="West Ham" /><T S="340" T="5" D="423" C="13:00" L="At Wembley Park Platform 4" DE="Stratford" /><T S="332" T="4" D="423" C="19:00" L="Between Queensbury and Kingsbury" DE="Stratford" /><T S="312" T="5" D="423" C="21:00" L="Leaving Canons Park" DE="Stratford" /><T S="333" T="5" D="423" C="24:00" L="At Stanmore Platform 1" DE="Stratford" /></P></S><S Code="WMS" N="Westminster."><P N="Eastbound - Platform 3" Code="1" Next="0"><T S="357" T="7" D="333" C="2:30" L="At Green Park Platform 6" DE="North Greenwich" /><T S="310" T="6" D="423" C="6:00" L="Approaching Bond Street" DE="Stratford" /><T S="321" T="5" D="423" C="7:00" L="Leaving Baker Street" DE="Stratford" /><T S="365" T="4" D="477" C="11:00" L="At St. John's Wood Platform 2" DE="West Ham" /><T S="337" T="5" D="423" C="12:00" L="At Swiss Cottage Platform 2" DE="Stratford" /><T S="350" T="6" D="423" C="15:00" L="At Finchley Road Platform 3" DE="Stratford" /><T S="331" T="5" D="423" C="17:00" L="Between Kilburn and West Hampstead" DE="Stratford" /><T S="360" T="5" D="333" C="20:00" L="Leaving Willesden Green" DE="North Greenwich" /><T S="311" T="4" D="423" C="23:00" L="Leaving Dollis Hill" DE="Stratford" /><T S="366" T="4" D="477" C="28:00" L="Between Wembley Park and Neasden" DE="West Ham" /><T S="340" T="5" D="423" C="29:00" L="At Wembley Park Platform 4" DE="Stratford" /></P><P N="Westbound - Platform 4" Code="0" Next="0"><T S="334" T="6" D="590" C="3:30" L="At Waterloo Platform 5" DE="Wembley Park" /><T S="372" T="5" D="416" C="5:00" L="Between London Bridge and Southwark" DE="Stanmore" /><T S="355" T="6" D="416" C="7:00" L="Between Bermondsey and London Bridge" DE="Stanmore" /><T S="336" T="5" D="416" C="10:00" L="Between Canada Water and Bermondsey" DE="Stanmore" /><T S="354" T="8" D="590" C="13:00" L="Between Canary Wharf and Canada Water" DE="Wembley Park" /><T S="316" T="5" D="416" C="15:00" L="Between North Greenwich and Canary Wharf" DE="Stanmore" /><T S="327" T="5" D="416" C="19:00" L="Between Canning Town and North Greenwich" DE="Stanmore" /><T S="325" T="5" D="496" C="21:00" L="Approaching Canning Town" DE="Willesden Green" /><T S="345" T="3" D="416" C="23:00" L="At West Ham Platform 5" DE="Stanmore" /></P></S><S Code="WLG" N="Willesden Green."><P N="Northbound - Platform 2" Code="0" Next="0"><T S="314" T="6" D="416" C="-" L="At Platform" DE="Stanmore" /><T S="371" T="5" D="416" C="3:00" L="Leaving West Hampstead" DE="Stanmore" /><T S="301" T="6" D="496" C="4:00" L="Between Finchley Road and West Hampstead" DE="Willesden Green" /><T S="343" T="6" D="416" C="6:00" L="At Finchley Road Platform 2" DE="Stanmore" /><T S="324" T="8" D="590" C="9:00" L="At St. John's Wood Platform 1" DE="Wembley Park" /><T S="335" T="6" D="416" C="12:00" L="Leaving Baker Street" DE="Stanmore" /><T S="304" T="4" D="416" C="14:00" L="Between Bond Street and Baker Street" DE="Stanmore" /><T S="352" T="6" D="496" C="17:00" L="Between Green Park and Bond Street" DE="Willesden Green" /><T S="326" T="6" D="416" C="19:00" L="Between Westminster and Green Park" DE="Stanmore" /><T S="334" T="6" D="590" C="23:00" L="At Waterloo Platform 5" DE="Wembley Park" /><T S="372" T="5" D="416" C="24:00" L="Between London Bridge and Southwark" DE="Stanmore" /><T S="355" T="6" D="416" C="26:00" L="Between Bermondsey and London Bridge" DE="Stanmore" /><T S="336" T="5" D="416" C="29:00" L="Between Canada Water and Bermondsey" DE="Stanmore" /></P><P N="Southbound - Platform 3" Code="1" Next="0"><T S="311" T="4" D="423" C="3:30" L="Leaving Dollis Hill" DE="Stratford" /><T S="366" T="4" D="477" C="7:00" L="Between Wembley Park and Neasden" DE="West Ham" /><T S="340" T="5" D="423" C="9:00" L="At Wembley Park Platform 4" DE="Stratford" /><T S="332" T="4" D="423" C="14:00" L="Between Queensbury and Kingsbury" DE="Stratford" /><T S="312" T="5" D="423" C="17:00" L="Leaving Canons Park" DE="Stratford" /><T S="333" T="5" D="423" C="20:00" L="At Stanmore Platform 1" DE="Stratford" /></P></S></ROOT>